piglatincli.py
piglatincli-0.1.0.dist-info/entry_points.txt
piglatincli-0.1.0.dist-info/WHEEL
piglatincli-0.1.0.dist-info/METADATA
piglatincli-0.1.0.dist-info/RECORD
