Metadata-Version: 2.1
Name: piglatincli
Version: 0.1.0
Summary: A cli to convert English to pig latin and vice versa
Home-page: https://github.com/AvanindraC/Pig-Latin-Cli
License: MIT
Author: Avanindra Chakraborty
Requires-Python: >=3.7,<4.0
Classifier: License :: OSI Approved :: MIT License
Classifier: Operating System :: OS Independent
Classifier: Programming Language :: Python :: 3
Classifier: Programming Language :: Python :: 3.6
Classifier: Programming Language :: Python :: 3.7
Classifier: Programming Language :: Python :: 3.8
Classifier: Programming Language :: Python :: 3.9
Requires-Dist: click (>=8.0.1,<9.0.0)
Requires-Dist: click-help-colors (>=0.9.1,<0.10.0)
Project-URL: Repository, https://github.com/AvanindraC/Pig-Latin-Cli
